aiopaypaython/__init__.py
aiopaypaython/main.py
aiopaypaython/pkce.py
aiopaypaython-1.8.8.dist-info/LICENSE
aiopaypaython-1.8.8.dist-info/METADATA
aiopaypaython-1.8.8.dist-info/WHEEL
aiopaypaython-1.8.8.dist-info/top_level.txt
aiopaypaython-1.8.8.dist-info/RECORD
